[
    {
        "id": "b2ef51efafb9e29917c5acba965b0ccb",
        "owner": "equestria-dev",
        "name": "libprisbeam",
        "display_name": "libprisbeam",
        "description": "A TypeScript library to work with Prisbeam databases in first-party as well as third-party consumers.",
        "source": "https:\/\/github.com\/equestria-dev\/libprisbeam",
        "icon": null,
        "website": "https:\/\/github.com\/equestria-dev\/libprisbeam",
        "size": 49152,
        "language": "TypeScript",
        "languages": {
            "TypeScript": 100
        },
        "update": 1718829470,
        "commit": 1718829467,
        "archive": false,
        "readme": null
    },
    {
        "id": "c66e979845d3a24cd3a517559b7b1936",
        "owner": "equestria-dev",
        "name": "maretimesans",
        "display_name": "maretimesans",
        "description": "A font based on the 2022 My Little Pony logo",
        "source": "https:\/\/github.com\/equestria-dev\/maretimesans",
        "icon": null,
        "website": "https:\/\/github.com\/equestria-dev\/maretimesans",
        "size": 1792000,
        "language": "TypeScript",
        "languages": {
            "TypeScript": 100
        },
        "update": 1718915792,
        "commit": 1718915790,
        "archive": false,
        "readme": null
    },
    {
        "id": "67bdcb236aa0cca0b8fd3fc8c7a22b93",
        "owner": "equestria-dev",
        "name": "ponypush",
        "display_name": "ponypush",
        "description": "A fork of the ntfy Android app made for Equestria.dev's notifications platform",
        "source": "https:\/\/github.com\/equestria-dev\/ponypush",
        "icon": null,
        "website": "https:\/\/github.com\/equestria-dev\/ponypush",
        "size": 58133504,
        "language": "Kotlin",
        "languages": {
            "Kotlin": 98.84156052772086,
            "Java": 0.9996303580962986,
            "JavaScript": 0.1588091141828404
        },
        "update": 1718288605,
        "commit": 1718288601,
        "archive": false,
        "readme": null
    },
    {
        "id": "d4fe44c9ab656861943dc43d78adb83f",
        "owner": "equestria-dev",
        "name": "autopush",
        "display_name": "autopush",
        "description": "A set of command-line utilities made for Equestria.dev",
        "source": "https:\/\/github.com\/equestria-dev\/autopush",
        "icon": null,
        "website": "https:\/\/github.com\/equestria-dev\/autopush",
        "size": 4316160,
        "language": "Rust",
        "languages": {
            "Rust": 100
        },
        "update": 1718917844,
        "commit": 1718917841,
        "archive": false,
        "readme": null
    },
    {
        "id": "3728b05eb842aaa2df4b6d7606b8a459",
        "owner": "equestria-dev",
        "name": "prisbeam",
        "display_name": "prisbeam",
        "description": "A browser and search engine for local copies of various image boards (Derpibooru, Furbooru, e621, ...)",
        "source": "https:\/\/github.com\/equestria-dev\/prisbeam",
        "icon": null,
        "website": "https:\/\/github.com\/equestria-dev\/prisbeam",
        "size": 4075520,
        "language": "TypeScript",
        "languages": {
            "TypeScript": 48.261565233640496,
            "JavaScript": 23.25718556929797,
            "HTML": 14.838302792473984,
            "Python": 6.072550599722037,
            "CSS": 5.203625194165119,
            "Shell": 2.366770610700396
        },
        "update": 1718787265,
        "commit": 1718787262,
        "archive": false,
        "readme": null
    },
    {
        "id": "35c010969e87e3e86364e1a553270e8e",
        "owner": "equestria-dev",
        "name": "starshine",
        "display_name": "starshine",
        "description": "Equestria.dev's new 2024 website",
        "source": "https:\/\/github.com\/equestria-dev\/starshine",
        "icon": null,
        "website": "https:\/\/github.com\/equestria-dev\/starshine",
        "size": 79011840,
        "language": "PHP",
        "languages": {
            "PHP": 58.755957472809484,
            "CSS": 28.100940975192472,
            "JavaScript": 12.564157399486742,
            "Shell": 0.5789441525113039
        },
        "update": 1718917961,
        "commit": 1718917958,
        "archive": false,
        "readme": null
    },
    {
        "id": "e96224630ba66f227a54ac4ba2251b91",
        "owner": "equestria-dev",
        "name": "status",
        "display_name": "status",
        "description": "A real-time status page and automated poller for Equestria.dev",
        "source": "https:\/\/github.com\/equestria-dev\/status",
        "icon": null,
        "website": "https:\/\/github.com\/equestria-dev\/status",
        "size": 6984704,
        "language": "JavaScript",
        "languages": {
            "JavaScript": 41.35804589803491,
            "Rust": 34.04905867802666,
            "CSS": 22.923251339837844,
            "Nix": 1.6524666758279511,
            "Shell": 0.017177408272639826
        },
        "update": 1718783844,
        "commit": 1718783840,
        "archive": false,
        "readme": null
    },
    {
        "id": "d42d5552d548688fc3c7a57f3f7260eb",
        "owner": "equestria-dev",
        "name": "sunny-starbot",
        "display_name": "sunny-starbot",
        "description": "An AI model trained to reproduce Sunny Starscout's voice accurately",
        "source": "https:\/\/github.com\/equestria-dev\/sunny-starbot",
        "icon": null,
        "website": "https:\/\/github.com\/equestria-dev\/sunny-starbot",
        "size": 75162624,
        "language": "PHP",
        "languages": {
            "PHP": 83.64502319221177,
            "Python": 9.48821742407173,
            "JavaScript": 6.568407312733574,
            "Shell": 0.2983520709829302
        },
        "update": 1718787394,
        "commit": 1718787390,
        "archive": false,
        "readme": null
    },
    {
        "id": "79d8aa1e4ccdedf397a5af3cb7540d80",
        "owner": "equestria-dev",
        "name": "violette",
        "display_name": "violette",
        "description": "Raindrops's personal website project, with a major focus on design and UI",
        "source": "https:\/\/github.com\/equestria-dev\/violette",
        "icon": null,
        "website": "https:\/\/github.com\/equestria-dev\/violette",
        "size": 8165376,
        "language": "Rust",
        "languages": {
            "Rust": 99.15078179101214,
            "Shell": 0.8492182089878632
        },
        "update": 1718288696,
        "commit": 1718288693,
        "archive": false,
        "readme": null
    },
    {
        "id": "b11d6f468e78ef52efd5a4af78f32879",
        "owner": "equestria-dev",
        "name": "where-rs",
        "display_name": "where-rs",
        "description": "A small Rust client (where) and server (whered) program to access a list of logged in users on multiple systems at once, similarly to who(1).",
        "source": "https:\/\/github.com\/equestria-dev\/where-rs",
        "icon": null,
        "website": "https:\/\/github.com\/equestria-dev\/where-rs",
        "size": 68608,
        "language": "Rust",
        "languages": {
            "Rust": 83.48852086146847,
            "Shell": 11.603525481555192,
            "Nix": 4.90795365697633
        },
        "update": 1718787283,
        "commit": 1718787279,
        "archive": false,
        "readme": null
    },
    {
        "id": "581c103a34cec5f021c003166ee20d42",
        "owner": "equestria-dev",
        "name": "wishing-star",
        "display_name": "wishing-star",
        "description": "A customizable and fast static wishlist page generator, primarily designed for use with Vercel",
        "source": "https:\/\/github.com\/equestria-dev\/wishing-star",
        "icon": null,
        "website": "https:\/\/github.com\/equestria-dev\/wishing-star",
        "size": 120832,
        "language": "PHP",
        "languages": {
            "PHP": 82.91870967741936,
            "JavaScript": 17.081290322580646
        },
        "update": 1718829475,
        "commit": 1718829471,
        "archive": false,
        "readme": null
    }
]